fb_login_brute/__init__.py
fb_login_brute/login_brute.py
fb_login_brute-1.0.4.dist-info/LICENSE
fb_login_brute-1.0.4.dist-info/METADATA
fb_login_brute-1.0.4.dist-info/WHEEL
fb_login_brute-1.0.4.dist-info/entry_points.txt
fb_login_brute-1.0.4.dist-info/top_level.txt
fb_login_brute-1.0.4.dist-info/RECORD
